<DOMSymbolItem xmlns="http://ns.adobe.com/xfl/2008/" xmlns:xsi="http://www.w3.org/2001/XMLSchema-instance" name="Symbol 648" itemID="69a20280-000000f3" lastModified="1772157771" symbolType="graphic">
     <timeline>
          <DOMTimeline name="Symbol 648" currentFrame="0">
               <layers>
                    <DOMLayer name="Layer 1">
                         <frames>
                              <DOMFrame index="0" motionTweenScale="false" keyMode="8192">
                                   <elements>
                                        <DOMShape isFloating="true">
                                             <fills>
                                                  <FillStyle index="1">
                                                       <SolidColor color="#000000"/>
                                                  </FillStyle>
                                             </fills>
                                             <strokes/>
                                             <edges>
                                                  <Edge fillStyle0="0" fillStyle1="1" strokeStyle="0" edges="! 193 -2121| 204 -2118[ 184 -2162 184 -2214[ 184 -2312 253 -2381[ 322 -2450 420 -2450[ 518 -2450 587 -2381[ 656 -2312 656 -2214[ 656 -2116 587 -2047[ 556 -2016 519 -1998| 614 -1948[ 695 -1907 770 -1958[ 830 -1998 903 -2008| 999 -2030[ 1076 -2055 1157 -2069| 1288 -2087[ 1300 -2102 1317 -2108| 1338 -2114[ 1446 -2095 1420 -1983[ 1404 -1910 1335 -1943| 1319 -1958[ 1206 -1964 1089 -1930[ 1114 -1904 1092 -1854[ 1081 -1829 1063 -1808[ 1120 -1791 1121 -1735[ 1121 -1705 1092 -1694[ 1024 -1669 975 -1713| 965 -1708[ 907 -1681 845 -1664[ 709 -1627 580 -1573[ 494 -1537 407 -1550[ 391 -1552 381 -1567[ 319 -1659 263 -1755[ 229 -1597 182 -1442[ 143 -1314 126 -1180| 119 -1150[ 134 -1131 143 -1104| 144 -1098[ 199 -1041 233 -968[ 270 -892 331 -829[ 394 -765 433 -686[ 459 -632 433 -577| 422 -550[ 346 -346 292 -132| 273 -55| 461 -44[ 528 -37 512 25[ 502 63 461 64| 245 75[ 217 77 190 67[ 126 43 143 -30[ 170 -145 212 -255[ 240 -415 298 -566[ 311 -599 317 -635| 314 -641| 312 -653| 312 -658[ 184 -805 86 -970| 81 -981[ 67 -966 60 -941[ 55 -925 43 -912[ 23 -779 17 -641| 17 -612[ 20 -549 -28 -510[ -59 -484 -81 -450[ -193 -279 -334 -128[ -298 -72 -251 -25| -240 -15[ -174 -27 -140 22[ -116 56 -148 82[ -193 118 -251 103[ -258 96 -269 95| -276 95[ -339 69 -385 14[ -436 -48 -459 -122[ -467 -147 -454 -169| -411 -226[ -266 -383 -146 -555| -112 -608[ -102 -624 -100 -645[ -83 -774 -75 -904[ -72 -951 -53 -992[ -17 -1068 -6 -1151| 0 -1172[ 8 -1279 41 -1381[ 108 -1586 150 -1802| 175 -1933[ 154 -1988 141 -2046[ 128 -2102 182 -2119| 193 -2121"/>
                                                  <Edge fillStyle0="0" fillStyle1="1" strokeStyle="0" edges="! 850 -1872[ 722 -1767 574 -1836[ 477 -1881 386 -1934| 340 -1958| 321 -1968| 306 -1936[ 376 -1798 454 -1666| 781 -1780[ 850 -1805 918 -1813[ 919 -1835 929 -1858| 950 -1893| 850 -1872"/>
                                             </edges>
                                        </DOMShape>
                                   </elements>
                              </DOMFrame>
                         </frames>
                    </DOMLayer>
               </layers>
          </DOMTimeline>
     </timeline>
</DOMSymbolItem>
