<DOMSymbolItem xmlns="http://ns.adobe.com/xfl/2008/" xmlns:xsi="http://www.w3.org/2001/XMLSchema-instance" name="Symbol 2326" itemID="69a20280-000002de" lastModified="1772157771" symbolType="graphic">
     <timeline>
          <DOMTimeline name="Symbol 2326" currentFrame="0">
               <layers>
                    <DOMLayer name="Layer 1">
                         <frames>
                              <DOMFrame index="0" motionTweenScale="false" keyMode="8192">
                                   <elements>
                                        <DOMShape isFloating="true">
                                             <fills>
                                                  <FillStyle index="1">
                                                       <SolidColor color="#666666"/>
                                                  </FillStyle>
                                             </fills>
                                             <strokes/>
                                             <edges>
                                                  <Edge fillStyle0="1" fillStyle1="0" strokeStyle="0" edges="! -34 -637[ -28 -594 -25 -551[ -19 -468 -26 -384[ -29 -353 -20 -329[ -64 -298 -91 -245| -103 -219[ -127 -170 -156 -124[ -194 -82 -200 -33| -207 -17[ -210 3 -198 13[ -193 20 -181 21| -175 21[ -99 37 -25 19[ 13 10 -3 -26[ -12 -47 -33 -48| -113 -45| -88 -87[ -58 -132 -44 -181[ 0 -232 35 -286[ 67 -314 57 -359[ 48 -401 47 -446| 43 -610| 216 -571| 216 -570[ 151 -445 69 -332[ 57 -324 56 -312[ 51 -303 57 -294[ 64 -282 73 -275[ 92 -251 120 -238| 165 -212[ 205 -187 246 -195[ 260 -198 261 -212[ 266 -272 198 -287[ 187 -290 177 -296| 148 -312| 155 -329| 300 -542[ 312 -560 316 -580[ 326 -625 290 -637[ 273 -647 247 -643| 39 -690| 39 -697| 34 -709| 34 -715[ 30 -812 45 -905[ 167 -817 307 -765[ 335 -754 353 -776[ 370 -799 364 -830[ 351 -887 289 -871| 266 -861[ 176 -900 97 -957[ 233 -912 370 -875[ 411 -863 448 -881[ 475 -893 475 -924[ 474 -961 440 -978[ 381 -1007 342 -961| 83 -1044| 80 -1043| 118 -1142| 120 -1154[ 154 -1251 177 -1352| 179 -1365[ 212 -1420 162 -1452| 154 -1455[ 107 -1432 106 -1371| 105 -1367[ 63 -1204 4 -1044| -9 -1007[ -35 -994 -19 -967[ -49 -831 -33 -690| -31 -683[ -38 -664 -34 -637"/>
                                             </edges>
                                        </DOMShape>
                                   </elements>
                              </DOMFrame>
                         </frames>
                    </DOMLayer>
               </layers>
          </DOMTimeline>
     </timeline>
</DOMSymbolItem>
