<DOMSymbolItem xmlns="http://ns.adobe.com/xfl/2008/" xmlns:xsi="http://www.w3.org/2001/XMLSchema-instance" name="Symbol 1302" itemID="69a20280-00000134" lastModified="1772157771" symbolType="graphic">
     <timeline>
          <DOMTimeline name="Symbol 1302" currentFrame="0">
               <layers>
                    <DOMLayer name="Layer 1">
                         <frames>
                              <DOMFrame index="0" motionTweenScale="false" keyMode="8192">
                                   <elements>
                                        <DOMShape isFloating="true">
                                             <fills>
                                                  <FillStyle index="1">
                                                       <SolidColor color="#000000"/>
                                                  </FillStyle>
                                             </fills>
                                             <strokes/>
                                             <edges>
                                                  <Edge fillStyle0="0" fillStyle1="1" strokeStyle="0" edges="! 165 -4019[ 243 -3961 257 -3864[ 271 -3767 213 -3689[ 195 -3665 174 -3647| 155 -3633[ 148 -3611 113 -3597| 84 -3587| 72 -3587| 71 -3588| 69 -3587| 63 -3588| 63 -3587| 364 -3546| 638 -3488| 785 -3461[ 844 -3453 891 -3421[ 907 -3410 910 -3389[ 922 -3286 823 -3259[ 754 -3239 704 -3281[ 673 -3307 680 -3348[ 500 -3402 305 -3429| 150 -3449| -22 -3473| -24 -3464[ -29 -3432 -22 -3401[ 24 -3208 0 -3010[ -1 -2997 -13 -2990[ -95 -2942 -173 -2887| -292 -2811[ -323 -2793 -359 -2802[ -459 -2827 -457 -2926[ -456 -2994 -388 -3008[ -323 -3021 -282 -2976| -111 -3078[ -119 -3217 -139 -3354| -186 -3288| -232 -3232[ -356 -3108 -506 -3018| -541 -2992[ -546 -2980 -556 -2971[ -598 -2937 -645 -2929| -646 -2927| -650 -2924[ -656 -2907 -669 -2892[ -781 -2764 -865 -2616[ -551 -2668 -238 -2704| -226 -2700[ -188 -2664 -185 -2607[ -183 -2570 -186 -2535[ -191 -2503 -183 -2471[ -169 -2415 -224 -2394[ -267 -2379 -287 -2419[ -304 -2455 -306 -2496| -307 -2577| -869 -2488[ -921 -2480 -972 -2486[ -1057 -2494 -1043 -2576[ -1038 -2608 -1017 -2631[ -949 -2710 -893 -2798| -880 -2819| -827 -2899[ -795 -2944 -755 -2982| -755 -2983| -802 -3281[ -819 -3391 -817 -3500| -1319 -3334[ -1331 -3331 -1342 -3339[ -1388 -3375 -1389 -3439[ -1390 -3488 -1406 -3533| -1420 -3589[ -1434 -3655 -1371 -3673[ -1289 -3660 -1290 -3569| -1285 -3543[ -1272 -3511 -1269 -3474| -762 -3647| -739 -3644[ -688 -3605 -696 -3537| -698 -3501[ -693 -3353 -664 -3205[ -652 -3139 -646 -3072[ -628 -3096 -598 -3111| -555 -3134[ -475 -3183 -402 -3243[ -276 -3349 -190 -3488| -173 -3498| -171 -3499| -154 -3532| -125 -3572| -125 -3594[ -123 -3610 -111 -3620| -102 -3645| -103 -3647[ -113 -3664 -137 -3673| -160 -3680| -162 -3683[ -165 -3711 -186 -3730| -194 -3736| -210 -3796[ -224 -3893 -166 -3971[ -108 -4050 -10 -4063[ 86 -4078 165 -4019"/>
                                             </edges>
                                        </DOMShape>
                                   </elements>
                              </DOMFrame>
                         </frames>
                    </DOMLayer>
               </layers>
          </DOMTimeline>
     </timeline>
</DOMSymbolItem>
